{
    "Title": "Sustentabilidad | Nearshoring News",
    "Description": "Prácticas y estrategias para la sostenibilidad.",
    "Type": "website",
    "Canonical": "sustentabilidad",
   "ImageFeatured": {
          "Width": "1200",
          "Height": "379",
          "Type": "image/png",
          "Url": "https://www.nearshoring.news/img/near/nearShoringLogoBlack.png"
        },
    "Index": true,
    "Follow": true,
    "Snippets": [],
    "Social": {
      "Facebook": {
        "Title": "Sustentabilidad | Nearshoring News",
        "Description": "Prácticas y estrategias para la sostenibilidad.",
        "ImageFeatured": {
          "Width": "1200",
          "Height": "379",
          "Type": "image/png",
          "Url": "https://www.nearshoring.news/img/near/nearShoringLogoBlack.png"
        }
      },
      "Twitter": {
        "Title": "Sustentabilidad | Nearshoring News",
        "Description": "Prácticas y estrategias para la sostenibilidad.",
        "ImageFeatured": {
          "Width": "1200",
          "Height": "379",
          "Type": "image/png",
          "Url": "https://www.nearshoring.news/img/near/nearShoringLogoBlack.png"
        },
        "Site": ""
      }
    }
  }
